Metadata-Version: 2.1
Name: tsm-core-models
Version: 0.0.4
Summary: Core Model library for The Social Matrix
Home-page: https://github.com/pypa/sampleproject
Author: Michael Duboc
Author-email: info@thesocialmatrix.com
License: MIT
Project-URL: Bug Tracker, https://github.com/pypa/sampleproject/issues
Classifier: Programming Language :: Python :: 3
Classifier: License :: OSI Approved :: MIT License
Classifier: Operating System :: OS Independent
Requires-Python: >=3.6
License-File: LICENSE
